exudyn/FEM.py
exudyn/GUI.py
exudyn/__init__.py
exudyn/__init__.pyi
exudyn/advancedUtilities.py
exudyn/artificialIntelligence.py
exudyn/basicUtilities.py
exudyn/beams.py
exudyn/demos.py
exudyn/exudynCPP.cpython-313-x86_64-linux-gnu.so
exudyn/exudynCPPfast.cpython-313-x86_64-linux-gnu.so
exudyn/graphics.py
exudyn/graphicsDataUtilities.py
exudyn/interactive.py
exudyn/itemInterface.py
exudyn/kinematicTree.py
exudyn/lieGroupBasics.py
exudyn/lieGroupIntegration.py
exudyn/machines.py
exudyn/mainSystemExtensions.py
exudyn/mainSystemInterface.py
exudyn/particles.py
exudyn/physics.py
exudyn/plot.py
exudyn/processing.py
exudyn/resultsMonitor.py
exudyn/rigidBodyUtilities.py
exudyn/signalProcessing.py
exudyn/solver.py
exudyn/symbolic.pyi
exudyn/utilities.py
exudyn/robotics/__init__.py
exudyn/robotics/future.py
exudyn/robotics/mobile.py
exudyn/robotics/models.py
exudyn/robotics/motion.py
exudyn/robotics/roboticsCore.py
exudyn/robotics/rosInterface.py
exudyn/robotics/special.py
exudyn/robotics/utilities.py
exudyn.libs/libXcursor-1a09904e.so.1.0.2
exudyn.libs/libXfixes-d274cb03.so.3.1.0
exudyn.libs/libXinerama-b7a62e01.so.1.0.0
exudyn.libs/libXrandr-1b5fae8f.so.2.2.0
exudyn.libs/libXxf86vm-3971cbbb.so.1.0.0
exudyn.libs/libglfw-14630bf2.so.3.2
exudyn-1.10.0.dist-info/METADATA
exudyn-1.10.0.dist-info/WHEEL
exudyn-1.10.0.dist-info/top_level.txt
exudyn-1.10.0.dist-info/RECORD
